everything2text4prompt
