Metadata-Version: 2.1
Name: everything2text4prompt
Version: 0.0.10
Summary: Convert many medium into text, and the text format is specialized for prompt input
Home-page: https://github.com/michaelthwan/everything2text4prompt
Author: michaethwan
Author-email: michaelthwan@gmail.com
License: MIT
Requires-Python: >=3.8
License-File: LICENSE
